alu.v
// alu.v
module alu (
    input  [3:0] A,      // First operand
    input  [3:0] B,      // Second operand
    input  [2:0] op,     // Operation select
    output reg [3:0] Y,  // Result
    output reg Cout,     // Carry out
    output reg Zero      // Zero flag
);
    always @(*) begin
        {Cout, Y} = 5'b0; // Default values
        case (op)
            3'b000: {Cout, Y} = A + B;      // Addition
            3'b001: {Cout, Y} = A - B;      // Subtraction
            3'b010: Y = A & B;              // AND
            3'b011: Y = A | B;              // OR
            3'b100: Y = A ^ B;              // XOR
            3'b101: Y = ~A;                 // NOT (on A)
            3'b110: Y = A << 1;              // Shift left
            3'b111: Y = A >> 1;              // Shift right
        endcase
        Zero = (Y == 4'b0000);
    end
endmodule

alu_tb.v
// tb_alu.v
`include "alu.v"
`timescale 1ns/1ps
module tb_alu;
    reg [3:0] A, B;
    reg [2:0] op;
    wire [3:0] Y;
    wire Cout, Zero;

    alu uut (
        .A(A), .B(B), .op(op),
        .Y(Y), .Cout(Cout), .Zero(Zero)
    );

    initial begin
        // Waveform dump setup
        $dumpfile("alu.vcd"); // Output file
        $dumpvars(0, tb_alu); // Dump all variables in tb_alu

        A = 2; // operand A
        B = 5; // operand B

        for (op = 0; op < 8; op = op + 1) begin
            #5 $dumpvars(A, B, op, Y, Cout, Zero);
                
        end

        #5 $finish;
    end
endmodule

alu.vcd
$date
	Sun Aug 17 17:27:15 2025
$end
$version
	Icarus Verilog
$end
$timescale
	1ps
$end
$scope module tb_alu $end
$var wire 1 ! Cout $end
$var wire 4 " Y [3:0] $end
$var wire 1 # Zero $end
$var reg 4 $ A [3:0] $end
$var reg 4 % B [3:0] $end
$var reg 3 & op [2:0] $end
$scope module uut $end
$var wire 4 ' A [3:0] $end
$var wire 4 ( B [3:0] $end
$var wire 3 ) op [2:0] $end
$var reg 1 * Cout $end
$var reg 4 + Y [3:0] $end
$var reg 1 , Zero $end
$upscope $end
$upscope $end
$enddefinitions $end
#0
$dumpvars
0,
b111 +
0*
b0 )
b101 (
b10 '
b0 &
b101 %
b10 $
0#
b111 "
0!
$end
#5000
1*
1!
b1101 +
b1101 "
b1 &
b1 )
#10000
1,
1#
0*
0!
b0 +
b0 "
b10 &
b10 )
#15000
0,
0#
b111 +
b111 "
b11 &
b11 )
#20000
b111 +
b111 "
b100 &
b100 )
#25000
b1101 +
b1101 "
b101 &
b101 )
#30000
b100 +
b100 "
b110 &
b110 )
#35000
b1 +
b1 "
b111 &
b111 )
#40000
b111 +
b111 "
b0 &
b0 )
#45000
1*
1!
b1101 +
b1101 "
b1 &
b1 )
#50000
1,
1#
0*
0!
b0 +
b0 "
b10 &
b10 )
#55000
0,
0#
b111 +
b111 "
b11 &
b11 )
#60000
b111 +
b111 "
b100 &
b100 )
#65000
b1101 +
b1101 "
b101 &
b101 )
#70000
b100 +
b100 "
b110 &
b110 )
#75000
b1 +
b1 "
b111 &
b111 )
#80000
b111 +
b111 "
b0 &
b0 )
#85000
1*
1!
b1101 +
b1101 "
b1 &
b1 )
#90000
1,
1#
0*
0!
b0 +
b0 "
b10 &
b10 )
#95000
0,
0#
b111 +
b111 "
b11 &
b11 )
#100000
b111 +
b111 "
b100 &
b100 )
#105000
b1101 +
b1101 "
b101 &
b101 )
#110000
b100 +
b100 "
b110 &
b110 )
#115000
b1 +
b1 "
b111 &
b111 )
#120000
b111 +
b111 "
b0 &
b0 )
#125000
1*
1!
b1101 +
b1101 "
b1 &
b1 )
#130000
1,
1#
0*
0!
b0 +
b0 "
b10 &
b10 )
#135000
0,
0#
b111 +
b111 "
b11 &
b11 )
#140000
b111 +
b111 "
b100 &
b100 )
#145000
b1101 +
b1101 "
b101 &
b101 )
#150000
b100 +
b100 "
b110 &
b110 )
#155000
b1 +
b1 "
b111 &
b111 )
#160000
b111 +
b111 "
b0 &
b0 )
#165000
1*
1!
b1101 +
b1101 "
b1 &
b1 )
#170000
1,
1#
0*
0!
b0 +
b0 "
b10 &
b10 )
#175000
0,
0#
b111 +
b111 "
b11 &
b11 )
#180000
b111 +
b111 "
b100 &
b100 )
#185000
b1101 +
b1101 "
b101 &
b101 )
#190000
b100 +
b100 "
b110 &
b110 )
#195000
b1 +
b1 "
b111 &
b111 )
#200000
b111 +
b111 "
b0 &
b0 )
#205000
1*
1!
b1101 +
b1101 "
b1 &
b1 )
#210000
1,
1#
0*
0!
b0 +
b0 "
b10 &
b10 )
#215000
0,
0#
b111 +
b111 "
b11 &
b11 )
#220000
b111 +
b111 "
b100 &
b100 )
#225000
b1101 +
b1101 "
b101 &
b101 )
#230000
b100 +
b100 "
b110 &
b110 )
#235000
b1 +
b1 "
b111 &
b111 )
#240000
b111 +
b111 "
b0 &
b0 )
#245000
1*
1!
b1101 +
b1101 "
b1 &
b1 )
#250000
1,
1#
0*
0!
b0 +
b0 "
b10 &
b10 )
#255000
0,
0#
b111 +
b111 "
b11 &
b11 )
#260000
b111 +
b111 "
b100 &
b100 )
#265000
b1101 +
b1101 "
b101 &
b101 )
#270000
b100 +
b100 "
b110 &
b110 )
#275000
b1 +
b1 "
b111 &
b111 )
#280000
b111 +
b111 "
b0 &
b0 )
#285000
1*
1!
b1101 +
b1101 "
b1 &
b1 )
#290000
1,
1#
0*
0!
b0 +
b0 "
b10 &
b10 )
#295000
0,
0#
b111 +
b111 "
b11 &
b11 )
#300000
b111 +
b111 "
b100 &
b100 )
#305000
b1101 +
b1101 "
b101 &
b101 )
#310000
b100 +
b100 "
b110 &
b110 )
#315000
b1 +
b1 "
b111 &
b111 )
#320000
b111 +
b111 "
b0 &
b0 )
#325000
1*
1!
b1101 +
b1101 "
b1 &
b1 )
#330000
1,
1#
0*
0!
b0 +
b0 "
b10 &
b10 )
#335000
0,
0#
b111 +
b111 "
b11 &
b11 )
#340000
b111 +
b111 "
b100 &
b100 )
#345000
b1101 +
b1101 "
b101 &
b101 )
#350000
b100 +
b100 "
b110 &
b110 )
#355000
b1 +
b1 "
b111 &
b111 )
#360000
b111 +
b111 "
b0 &
b0 )
#365000
1*
1!
b1101 +
b1101 "
b1 &
b1 )
#370000
1,
1#
0*
0!
b0 +
b0 "
b10 &
b10 )
#375000
0,
0#
b111 +
b111 "
b11 &
b11 )
#380000
b111 +
b111 "
b100 &
b100 )
#385000
b1101 +
b1101 "
b101 &
b101 )
#390000
b100 +
b100 "
b110 &
b110 )
#395000
b1 +
b1 "
b111 &
b111 )
#400000
b111 +
b111 "
b0 &
b0 )
#405000
1*
1!
b1101 +
b1101 "
b1 &
b1 )
#410000
1,
1#
0*
0!
b0 +
b0 "
b10 &
b10 )
#415000
0,
0#
b111 +
b111 "
b11 &
b11 )
#420000
b111 +
b111 "
b100 &
b100 )
#425000
b1101 +
b1101 "
b101 &
b101 )
#430000
b100 +
b100 "
b110 &
b110 )
#435000
b1 +
b1 "
b111 &
b111 )
#440000
b111 +
b111 "
b0 &
b0 )
#445000
1*
1!
b1101 +
b1101 "
b1 &
b1 )
#450000
1,
1#
0*
0!
b0 +
b0 "
b10 &
b10 )
#455000
0,
0#
b111 +
b111 "
b11 &
b11 )
#460000
b111 +
b111 "
b100 &
b100 )
#465000
b1101 +
b1101 "
b101 &
b101 )
#470000
b100 +
b100 "
b110 &
b110 )
#475000
b1 +
b1 "
b111 &
b111 )
#480000
b111 +
b111 "
b0 &
b0 )
#485000
1*
1!
b1101 +
b1101 "
b1 &
b1 )
#490000
1,
1#
0*
0!
b0 +
b0 "
b10 &
b10 )
#495000
0,
0#
b111 +
b111 "
b11 &
b11 )
#500000
b111 +
b111 "
b100 &
b100 )
#505000
b1101 +
b1101 "
b101 &
b101 )
#510000
b100 +
b100 "
b110 &
b110 )
#515000
b1 +
b1 "
b111 &
b111 )
#520000
b111 +
b111 "
b0 &
b0 )
#525000
1*
1!
b1101 +
b1101 "
b1 &
b1 )
#530000
1,
1#
0*
0!
b0 +
b0 "
b10 &
b10 )
#535000
0,
0#
b111 +
b111 "
b11 &
b11 )
#540000
b111 +
b111 "
b100 &
b100 )
#545000
b1101 +
b1101 "
b101 &
b101 )
#550000
b100 +
b100 "
b110 &
b110 )
#555000
b1 +
b1 "
b111 &
b111 )
#560000
b111 +
b111 "
b0 &
b0 )
#565000
1*
1!
b1101 +
b1101 "
b1 &
b1 )
#570000
1,
1#
0*
0!
b0 +
b0 "
b10 &
b10 )
#575000
0,
0#
b111 +
b111 "
b11 &
b11 )
#580000
b111 +
b111 "
b100 &
b100 )
#585000
b1101 +
b1101 "
b101 &
b101 )
#590000
b100 +
b100 "
b110 &
b110 )
#595000
b1 +
b1 "
b111 &
b111 )
#600000
b111 +
b111 "
b0 &
b0 )
#605000
1*
1!
b1101 +
b1101 "
b1 &
b1 )
#610000
1,
1#
0*
0!
b0 +
b0 "
b10 &
b10 )
#615000
0,
0#
b111 +
b111 "
b11 &
b11 )
#620000
b111 +
b111 "
b100 &
b100 )
#625000
b1101 +
b1101 "
b101 &
b101 )
#630000
b100 +
b100 "
b110 &
b110 )
#635000
b1 +
b1 "
b111 &
b111 )
#640000
b111 +
b111 "
b0 &
b0 )
#645000
1*
1!
b1101 +
b1101 "
b1 &
b1 )
#650000
1,
1#
0*
0!
b0 +
b0 "
b10 &
b10 )
#655000
0,
0#
b111 +
b111 "
b11 &
b11 )
#660000
b111 +
b111 "
b100 &
b100 )
#665000
b1101 +
b1101 "
b101 &
b101 )
#670000
b100 +
b100 "
b110 &
b110 )
#675000
b1 +
b1 "
b111 &
b111 )
#680000
b111 +
b111 "
b0 &
b0 )
#685000
1*
1!
b1101 +
b1101 "
b1 &
b1 )
#690000
1,
1#
0*
0!
b0 +
b0 "
b10 &
b10 )
#695000
0,
0#
b111 +
b111 "
b11 &
b11 )
#700000
b111 +
b111 "
b100 &
b100 )
#705000
b1101 +
b1101 "
b101 &
b101 )
#710000
b100 +
b100 "
b110 &
b110 )
#715000
b1 +
b1 "
b111 &
b111 )
#720000
b111 +
b111 "
b0 &
b0 )
#725000
1*
1!
b1101 +
b1101 "
b1 &
b1 )
#730000
1,
1#
0*
0!
b0 +
b0 "
b10 &
b10 )
#735000
0,
0#
b111 +
b111 "
b11 &
b11 )
#740000
b111 +
b111 "
b100 &
b100 )
#745000
b1101 +
b1101 "
b101 &
b101 )
#750000
b100 +
b100 "
b110 &
b110 )
#755000
b1 +
b1 "
b111 &
b111 )
#760000
b111 +
b111 "
b0 &
b0 )
#765000
1*
1!
b1101 +
b1101 "
b1 &
b1 )
#770000
1,
1#
0*
0!
b0 +
b0 "
b10 &
b10 )
#775000
0,
0#
b111 +
b111 "
b11 &
b11 )
#780000
b111 +
b111 "
b100 &
b100 )
#785000
b1101 +
b1101 "
b101 &
b101 )
#790000
b100 +
b100 "
b110 &
b110 )
#795000
b1 +
b1 "
b111 &
b111 )
#800000
b111 +
b111 "
b0 &
b0 )
#805000
1*
1!
b1101 +
b1101 "
b1 &
b1 )
#810000
1,
1#
0*
0!
b0 +
b0 "
b10 &
b10 )
#815000
0,
0#
b111 +
b111 "
b11 &
b11 )
#820000
b111 +
b111 "
b100 &
b100 )
#825000
b1101 +
b1101 "
b101 &
b101 )
#830000
b100 +
b100 "
b110 &
b110 )
#835000
b1 +
b1 "
b111 &
b111 )
#840000
b111 +
b111 "
b0 &
b0 )
#845000
1*
1!
b1101 +
b1101 "
b1 &
b1 )
#850000
1,
1#
0*
0!
b0 +
b0 "
b10 &
b10 )
#855000
0,
0#
b111 +
b111 "
b11 &
b11 )
#860000
b111 +
b111 "
b100 &
b100 )
#865000
b1101 +
b1101 "
b101 &
b101 )
#870000
b100 +
b100 "
b110 &
b110 )
#875000
b1 +
b1 "
b111 &
b111 )
#880000
b111 +
b111 "
b0 &
b0 )
#885000
1*
1!
b1101 +
b1101 "
b1 &
b1 )
#890000
1,
1#
0*
0!
b0 +
b0 "
b10 &
b10 )
#895000
0,
0#
b111 +
b111 "
b11 &
b11 )
#900000
b111 +
b111 "
b100 &
b100 )
#905000
b1101 +
b1101 "
b101 &
b101 )
#910000
b100 +
b100 "
b110 &
b110 )
#915000
b1 +
b1 "
b111 &
b111 )
#920000
b111 +
b111 "
b0 &
b0 )
#925000
1*
1!
b1101 +
b1101 "
b1 &
b1 )
#930000
1,
1#
0*
0!
b0 +
b0 "
b10 &
b10 )
#935000
0,
0#
b111 +
b111 "
b11 &
b11 )
#940000
b111 +
b111 "
b100 &
b100 )
#945000
b1101 +
b1101 "
b101 &
b101 )
#950000
b100 +
b100 "
b110 &
b110 )
#955000
b1 +
b1 "
b111 &
b111 )
#960000
b111 +
b111 "
b0 &
b0 )
#965000
1*
1!
b1101 +
b1101 "
b1 &
b1 )
#970000
1,
1#
0*
0!
b0 +
b0 "
b10 &
b10 )
#975000
0,
0#
b111 +
b111 "
b11 &
b11 )
#980000
b111 +
b111 "
b100 &
b100 )
#985000
b1101 +
b1101 "
b101 &
b101 )
#990000
b100 +
b100 "
b110 &
b110 )
#995000
b1 +
b1 "
b111 &
b111 )
#1000000
b111 +
b111 "
b0 &
b0 )
#1005000
1*
1!
b1101 +
b1101 "
b1 &
b1 )
#1010000
1,
1#
0*
0!
b0 +
b0 "
b10 &
b10 )
#1015000
0,
0#
b111 +
b111 "
b11 &
b11 )
#1020000
b111 +
b111 "
b100 &
b100 )
#1025000
b1101 +
b1101 "
b101 &
b101 )
#1030000
b100 +
b100 "
b110 &
b110 )
#1035000
b1 +
b1 "
b111 &
b111 )
#1040000
b111 +
b111 "
b0 &
b0 )
#1045000
1*
1!
b1101 +
b1101 "
b1 &
b1 )
#1050000
1,
1#
0*
0!
b0 +
b0 "
b10 &
b10 )
#1055000
0,
0#
b111 +
b111 "
b11 &
b11 )
#1060000
b111 +
b111 "
b100 &
b100 )
#1065000
b1101 +
b1101 "
b101 &
b101 )
#1070000
b100 +
b100 "
b110 &
b110 )
#1075000
b1 +
b1 "
b111 &
b111 )
#1080000
b111 +
b111 "
b0 &
b0 )
#1085000
1*
1!
b1101 +
b1101 "
b1 &
b1 )
#1090000
1,
1#
0*
0!
b0 +
b0 "
b10 &
b10 )
#1095000
0,
0#
b111 +
b111 "
b11 &
b11 )
#1100000
b111 +
b111 "
b100 &
b100 )
#1105000
b1101 +
b1101 "
b101 &
b101 )
#1110000
b100 +
b100 "
b110 &
b110 )
#1115000
b1 +
b1 "
b111 &
b111 )
#1120000
b111 +
b111 "
b0 &
b0 )
#1125000
1*
1!
b1101 +
b1101 "
b1 &
b1 )
#1130000
1,
1#
0*
0!
b0 +
b0 "
b10 &
b10 )
#1135000
0,
0#
b111 +
b111 "
b11 &
b11 )
#1140000
b111 +
b111 "
b100 &
b100 )
#1145000
b1101 +
b1101 "
b101 &
b101 )
#1150000
b100 +
b100 "
b110 &
b110 )
#1155000
b1 +
b1 "
b111 &
b111 )
#1160000
b111 +
b111 "
b0 &
b0 )
#1165000
1*
1!
b1101 +
b1101 "
b1 &
b1 )
#1170000
1,
1#
0*
0!
b0 +
b0 "
b10 &
b10 )
#1175000
0,
0#
b111 +
b111 "
b11 &
b11 )
#1180000
b111 +
b111 "
b100 &
b100 )
#1185000
b1101 +
b1101 "
b101 &
b101 )
#1190000
b100 +
b100 "
b110 &
b110 )
#1195000
b1 +
b1 "
b111 &
b111 )
#1200000
b111 +
b111 "
b0 &
b0 )
#1205000
1*
1!
b1101 +
b1101 "
b1 &
b1 )
#1210000
1,
1#
0*
0!
b0 +
b0 "
b10 &
b10 )
#1215000
0,
0#
b111 +
b111 "
b11 &
b11 )
#1220000
b111 +
b111 "
b100 &
b100 )
#1225000
b1101 +
b1101 "
b101 &
b101 )
#1230000
b100 +
b100 "
b110 &
b110 )
#1235000
b1 +
b1 "
b111 &
b111 )
#1240000
b111 +
b111 "
b0 &
b0 )
#1245000
1*
1!
b1101 +
b1101 "
b1 &
b1 )
#1250000
1,
1#
0*
0!
b0 +
b0 "
b10 &
b10 )
#1255000
0,
0#
b111 +
b111 "
b11 &
b11 )
#1260000
b111 +
b111 "
b100 &
b100 )
#1265000
b1101 +
b1101 "
b101 &
b101 )
#1270000
b100 +
b100 "
b110 &
b110 )
#1275000
b1 +
b1 "
b111 &
b111 )
#1280000
b111 +
b111 "
b0 &
b0 )
#1285000
1*
1!
b1101 +
b1101 "
b1 &
b1 )
#1290000
1,
1#
0*
0!
b0 +
b0 "
b10 &
b10 )
#1295000
0,
0#
b111 +
b111 "
b11 &
b11 )
#1300000
b111 +
b111 "
b100 &
b100 )
#1305000
b1101 +
b1101 "
b101 &
b101 )
#1310000
b100 +
b100 "
b110 &
b110 )
#1315000
b1 +
b1 "
b111 &
b111 )
#1320000
b111 +
b111 "
b0 &
b0 )
#1325000
1*
1!
b1101 +
b1101 "
b1 &
b1 )
#1330000
1,
1#
0*
0!
b0 +
b0 "
b10 &
b10 )
#1335000
0,
0#
b111 +
b111 "
b11 &
b11 )
#1340000
b111 +
b111 "
b100 &
b100 )
#1345000
b1101 +
b1101 "
b101 &
b101 )
#1350000
b100 +
b100 "
b110 &
b110 )
#1355000
b1 +
b1 "
b111 &
b111 )
#1360000
b111 +
b111 "
b0 &
b0 )
#1365000
1*
1!
b1101 +
b1101 "
b1 &
b1 )
#1370000
1,
1#
0*
0!
b0 +
b0 "
b10 &
b10 )
#1375000
0,
0#
b111 +
b111 "
b11 &
b11 )
#1380000
b111 +
b111 "
b100 &
b100 )
#1385000
b1101 +
b1101 "
b101 &
b101 )
#1390000
b100 +
b100 "
b110 &
b110 )
#1395000
b1 +
b1 "
b111 &
b111 )
#1400000
b111 +
b111 "
b0 &
b0 )
#1405000
1*
1!
b1101 +
b1101 "
b1 &
b1 )
#1410000
1,
1#
0*
0!
b0 +
b0 "
b10 &
b10 )
#1415000
0,
0#
b111 +
b111 "
b11 &
b11 )
#1420000
b111 +
b111 "
b100 &
b100 )
#1425000
b1101 +
b1101 "
b101 &
b101 )
#1430000
b100 +
b100 "
b110 &
b110 )
#1435000
b1 +
b1 "
b111 &
b111 )
#1440000
b111 +
b111 "
b0 &
b0 )
#1445000
1*
1!
b1101 +
b1101 "
b1 &
b1 )
#1450000
1,
1#
0*
0!
b0 +
b0 "
b10 &
b10 )
#1455000
0,
0#
b111 +
b111 "
b11 &
b11 )
#1460000
b111 +
b111 "
b100 &
b100 )
#1465000
b1101 +
b1101 "
b101 &
b101 )
#1470000
b100 +
b100 "
b110 &
b110 )
#1475000
b1 +
b1 "
b111 &
b111 )
#1480000
b111 +
b111 "
b0 &
b0 )
#1485000
1*
1!
b1101 +
b1101 "
b1 &
b1 )
#1490000
1,
1#
0*
0!
b0 +
b0 "
b10 &
b10 )
#1495000
0,
0#
b111 +
b111 "
b11 &
b11 )
#1500000
b111 +
b111 "
b100 &
b100 )
#1505000
b1101 +
b1101 "
b101 &
b101 )
#1510000
b100 +
b100 "
b110 &
b110 )
#1515000
b1 +
b1 "
b111 &
b111 )
#1520000
b111 +
b111 "
b0 &
b0 )
#1525000
1*
1!
b1101 +
b1101 "
b1 &
b1 )
#1530000
1,
1#
0*
0!
b0 +
b0 "
b10 &
b10 )
#1535000
0,
0#
b111 +
b111 "
b11 &
b11 )
#1540000
b111 +
b111 "
b100 &
b100 )
#1545000
b1101 +
b1101 "
b101 &
b101 )
#1550000
b100 +
b100 "
b110 &
b110 )
#1555000
b1 +
b1 "
b111 &
b111 )
#1560000
b111 +
b111 "
b0 &
b0 )
#1565000
1*
1!
b1101 +
b1101 "
b1 &
b1 )
#1570000
1,
1#
0*
0!
b0 +
b0 "
b10 &
b10 )
#1575000
0,
0#
b111 +
b111 "
b11 &
b11 )
#1580000
b111 +
b111 "
b100 &
b100 )
#1585000
b1101 +
b1101 "
b101 &
b101 )
#1590000
b100 +
b100 "
b110 &
b110 )
#1595000
b1 +
b1 "
b111 &
b111 )
#1600000
b111 +
b111 "
b0 &
b0 )
#1605000
1*
1!
b1101 +
b1101 "
b1 &
b1 )
#1610000
1,
1#
0*
0!
b0 +
b0 "
b10 &
b10 )
#1615000
0,
0#
b111 +
b111 "
b11 &
b11 )
#1620000
b111 +
b111 "
b100 &
b100 )
#1625000
b1101 +
b1101 "
b101 &
b101 )
#1630000
b100 +
b100 "
b110 &
b110 )
#1635000
b1 +
b1 "
b111 &
b111 )
#1640000
b111 +
b111 "
b0 &
b0 )
#1645000
1*
1!
b1101 +
b1101 "
b1 &
b1 )
#1650000
1,
1#
0*
0!
b0 +
b0 "
b10 &
b10 )
#1655000
0,
0#
b111 +
b111 "
b11 &
b11 )
#1660000
b111 +
b111 "
b100 &
b100 )
#1665000
b1101 +
b1101 "
b101 &
b101 )
#1670000
b100 +
b100 "
b110 &
b110 )
#1675000
b1 +
b1 "
b111 &
b111 )
#1680000
b111 +
b111 "
b0 &
b0 )
#1685000
1*
1!
b1101 +
b1101 "
b1 &
b1 )
#1690000
1,
1#
0*
0!
b0 +
b0 "
b10 &
b10 )
#1695000
0,
0#
b111 +
b111 "
b11 &
b11 )
#1700000
b111 +
b111 "
b100 &
b100 )
#1705000
b1101 +
b1101 "
b101 &
b101 )
#1710000
b100 +
b100 "
b110 &
b110 )
#1715000
b1 +
b1 "
b111 &
b111 )
#1720000
b111 +
b111 "
b0 &
b0 )
#1725000
1*
1!
b1101 +
b1101 "
b1 &
b1 )
#1730000
1,
1#
0*
0!
b0 +
b0 "
b10 &
b10 )
#1735000
0,
0#
b111 +
b111 "
b11 &
b11 )
#1740000
b111 +
b111 "
b100 &
b100 )
#1745000
b1101 +
b1101 "
b101 &
b101 )
#1750000
b100 +
b100 "
b110 &
b110 )
#1755000
b1 +
b1 "
b111 &
b111 )
#1760000
b111 +
b111 "
b0 &
b0 )
#1765000
1*
1!
b1101 +
b1101 "
b1 &
b1 )
#1770000
1,
1#
0*
0!
b0 +
b0 "
b10 &
b10 )
#1775000
0,
0#
b111 +
b111 "
b11 &
b11 )
#1780000
b111 +
b111 "
b100 &
b100 )
#1785000
b1101 +
b1101 "
b101 &
b101 )
#1790000
b100 +
b100 "
b110 &
b110 )
#1795000
b1 +
b1 "
b111 &
b111 )
#1800000
b111 +
b111 "
b0 &
b0 )
#1805000
1*
1!
b1101 +
b1101 "
b1 &
b1 )
#1810000
1,
1#
0*
0!
b0 +
b0 "
b10 &
b10 )
#1815000
0,
0#
b111 +
b111 "
b11 &
b11 )
#1820000
b111 +
b111 "
b100 &
b100 )
#1825000
b1101 +
b1101 "
b101 &
b101 )
#1830000
b100 +
b100 "
b110 &
b110 )
#1835000
b1 +
b1 "
b111 &
b111 )
#1840000
b111 +
b111 "
b0 &
b0 )
#1845000
1*
1!
b1101 +
b1101 "
b1 &
b1 )
#1850000
1,
1#
0*
0!
b0 +
b0 "
b10 &
b10 )
#1855000
0,
0#
b111 +
b111 "
b11 &
b11 )
#1860000
b111 +
b111 "
b100 &
b100 )
#1865000
b1101 +
b1101 "
b101 &
b101 )
#1870000
b100 +
b100 "
b110 &
b110 )
#1875000
b1 +
b1 "
b111 &
b111 )
#1880000
b111 +
b111 "
b0 &
b0 )
#1885000
1*
1!
b1101 +
b1101 "
b1 &
b1 )
#1890000
1,
1#
0*
0!
b0 +
b0 "
b10 &
b10 )
#1895000
0,
0#
b111 +
b111 "
b11 &
b11 )
#1900000
b111 +
b111 "
b100 &
b100 )
#1905000
b1101 +
b1101 "
b101 &
b101 )
#1910000
b100 +
b100 "
b110 &
b110 )
#1915000
b1 +
b1 "
b111 &
b111 )
#1920000
b111 +
b111 "
b0 &
b0 )
#1925000
1*
1!
b1101 +
b1101 "
b1 &
b1 )
#1930000
1,
1#
0*
0!
b0 +
b0 "
b10 &
b10 )
#1935000
0,
0#
b111 +
b111 "
b11 &
b11 )
#1940000
b111 +
b111 "
b100 &
b100 )
#1945000
b1101 +
b1101 "
b101 &
b101 )
#1950000
b100 +
b100 "
b110 &
b110 )
#1955000
b1 +
b1 "
b111 &
b111 )
#1960000
b111 +
b111 "
b0 &
b0 )
#1965000
1*
1!
b1101 +
b1101 "
b1 &
b1 )
#1970000
1,
1#
0*
0!
b0 +
b0 "
b10 &
b10 )
#1975000
0,
0#
b111 +
b111 "
b11 &
b11 )
#1980000
b111 +
b111 "
b100 &
b100 )
#1985000
b1101 +
b1101 "
b101 &
b101 )
#1990000
b100 +
b100 "
b110 &
b110 )
#1995000
b1 +
b1 "
b111 &
b111 )
#2000000
b111 +
b111 "
b0 &
b0 )
#2005000
1*
1!
b1101 +
b1101 "
b1 &
b1 )
#2010000
1,
1#
0*
0!
b0 +
b0 "
b10 &
b10 )
#2015000
0,
0#
b111 +
b111 "
b11 &
b11 )
#2020000
b111 +
b111 "
b100 &
b100 )
#2025000
b1101 +
b1101 "
b101 &
b101 )
#2030000
b100 +
b100 "
b110 &
b110 )
#2035000
b1 +
b1 "
b111 &
b111 )
#2040000
b111 +
b111 "
b0 &
b0 )
#2045000
1*
1!
b1101 +
b1101 "
b1 &
b1 )
#2050000
1,
1#
0*
0!
b0 +
b0 "
b10 &
b10 )
#2055000
0,
0#
b111 +
b111 "
b11 &
b11 )
#2060000
b111 +
b111 "
b100 &
b100 )
#2065000
b1101 +
b1101 "
b101 &
b101 )
#2070000
b100 +
b100 "
b110 &
b110 )
#2075000
b1 +
b1 "
b111 &
b111 )
#2080000
b111 +
b111 "
b0 &
b0 )
#2085000
1*
1!
b1101 +
b1101 "
b1 &
b1 )
#2090000
1,
1#
0*
0!
b0 +
b0 "
b10 &
b10 )
#2095000
0,
0#
b111 +
b111 "
b11 &
b11 )
#2100000
b111 +
b111 "
b100 &
b100 )
#2105000
b1101 +
b1101 "
b101 &
b101 )
#2110000
b100 +
b100 "
b110 &
b110 )
#2115000
b1 +
b1 "
b111 &
b111 )
#2120000
b111 +
b111 "
b0 &
b0 )
#2125000
1*
1!
b1101 +
b1101 "
b1 &
b1 )
#2130000
1,
1#
0*
0!
b0 +
b0 "
b10 &
b10 )
#2135000
0,
0#
b111 +
b111 "
b11 &
b11 )
#2140000
b111 +
b111 "
b100 &
b100 )
#2145000
b1101 +
b1101 "
b101 &
b101 )
#2150000
b100 +
b100 "
b110 &
b110 )
#2155000
b1 +
b1 "
b111 &
b111 )
#2160000
b111 +
b111 "
b0 &
b0 )
#2165000
1*
1!
b1101 +
b1101 "
b1 &
b1 )
#2170000
1,
1#
0*
0!
b0 +
b0 "
b10 &
b10 )
#2175000
0,
0#
b111 +
b111 "
b11 &
b11 )
#2180000
b111 +
b111 "
b100 &
b100 )
#2185000
b1101 +
b1101 "
b101 &
b101 )
#2190000
b100 +
b100 "
b110 &
b110 )
#2195000
b1 +
b1 "
b111 &
b111 )
#2200000
b111 +
b111 "
b0 &
b0 )
#2205000
1*
1!
b1101 +
b1101 "
b1 &
b1 )
#2210000
1,
1#
0*
0!
b0 +
b0 "
b10 &
b10 )
#2215000
0,
0#
b111 +
b111 "
b11 &
b11 )
#2220000
b111 +
b111 "
b100 &
b100 )
#2225000
b1101 +
b1101 "
b101 &
b101 )
#2230000
b100 +
b100 "
b110 &
b110 )
#2235000
b1 +
b1 "
b111 &
b111 )
#2240000
b111 +
b111 "
b0 &
b0 )
#2245000
1*
1!
b1101 +
b1101 "
b1 &
b1 )
#2250000
1,
1#
0*
0!
b0 +
b0 "
b10 &
b10 )
#2255000
0,
0#
b111 +
b111 "
b11 &
b11 )
#2260000
b111 +
b111 "
b100 &
b100 )
#2265000
b1101 +
b1101 "
b101 &
b101 )
#2270000
b100 +
b100 "
b110 &
b110 )
#2275000
b1 +
b1 "
b111 &
b111 )
#2280000
b111 +
b111 "
b0 &
b0 )
#2285000
1*
1!
b1101 +
b1101 "
b1 &
b1 )
#2290000
1,
1#
0*
0!
b0 +
b0 "
b10 &
b10 )
#2295000
0,
0#
b111 +
b111 "
b11 &
b11 )
#2300000
b111 +
b111 "
b100 &
b100 )
#2305000
b1101 +
b1101 "
b101 &
b101 )
#2310000
b100 +
b100 "
b110 &
b110 )
#2315000
b1 +
b1 "
b111 &
b111 )
#2320000
b111 +
b111 "
b0 &
b0 )
#2325000
1*
1!
b1101 +
b1101 "
b1 &
b1 )
#2330000
1,
1#
0*
0!
b0 +
b0 "
b10 &
b10 )
#2335000
0,
0#
b111 +
b111 "
b11 &
b11 )
#2340000
b111 +
b111 "
b100 &
b100 )
#2345000
b1101 +
b1101 "
b101 &
b101 )
#2350000
b100 +
b100 "
b110 &
b110 )
#2355000
b1 +
b1 "
b111 &
b111 )
#2360000
b111 +
b111 "
b0 &
b0 )
#2365000
1*
1!
b1101 +
b1101 "
b1 &
b1 )
#2370000
1,
1#
0*
0!
b0 +
b0 "
b10 &
b10 )
#2375000
0,
0#
b111 +
b111 "
b11 &
b11 )
#2380000
b111 +
b111 "
b100 &
b100 )
#2385000
b1101 +
b1101 "
b101 &
b101 )
#2390000
b100 +
b100 "
b110 &
b110 )
#2395000
b1 +
b1 "
b111 &
b111 )
#2400000
b111 +
b111 "
b0 &
b0 )
#2405000
1*
1!
b1101 +
b1101 "
b1 &
b1 )
#2410000
1,
1#
0*
0!
b0 +
b0 "
b10 &
b10 )
#2415000
0,
0#
b111 +
b111 "
b11 &
b11 )
#2420000
b111 +
b111 "
b100 &
b100 )
#2425000
b1101 +
b1101 "
b101 &
b101 )
#2430000
b100 +
b100 "
b110 &
b110 )
#2435000
b1 +
b1 "
b111 &
b111 )
#2440000
b111 +
b111 "
b0 &
b0 )
#2445000
1*
1!
b1101 +
b1101 "
b1 &
b1 )
#2450000
1,
1#
0*
0!
b0 +
b0 "
b10 &
b10 )
#2455000
0,
0#
b111 +
b111 "
b11 &
b11 )
#2460000
b111 +
b111 "
b100 &
b100 )
#2465000
b1101 +
b1101 "
b101 &
b101 )
#2470000
b100 +
b100 "
b110 &
b110 )
#2475000
b1 +
b1 "
b111 &
b111 )
#2480000
b111 +
b111 "
b0 &
b0 )
